symphony_binary_confusion_matrix/__init__.py
symphony_binary_confusion_matrix/_frontend.py
symphony_binary_confusion_matrix/_version.py
symphony_binary_confusion_matrix/widget.py
symphony_binary_confusion_matrix/labextension/build_log.json
symphony_binary_confusion_matrix/labextension/package.json
symphony_binary_confusion_matrix/labextension/static/lib_index_js.38fdccc80145efd3325d.js
symphony_binary_confusion_matrix/labextension/static/lib_index_js.38fdccc80145efd3325d.js.map
symphony_binary_confusion_matrix/labextension/static/lib_index_js.9e2bc8e56ffb45e5ca40.js
symphony_binary_confusion_matrix/labextension/static/lib_index_js.9e2bc8e56ffb45e5ca40.js.map
symphony_binary_confusion_matrix/labextension/static/remoteEntry.6ba990506dbc68af9fb8.js
symphony_binary_confusion_matrix/labextension/static/remoteEntry.6ba990506dbc68af9fb8.js.map
symphony_binary_confusion_matrix/labextension/static/remoteEntry.a4dc19c9581bc55734f2.js
symphony_binary_confusion_matrix/labextension/static/remoteEntry.a4dc19c9581bc55734f2.js.map
symphony_binary_confusion_matrix/labextension/static/style.js
symphony_binary_confusion_matrix/nbextension/extension.js
symphony_binary_confusion_matrix/nbextension/index.js
symphony_binary_confusion_matrix/standalone/widgets/SymphonyBinaryConfusionMatrix.js
symphony_binary_confusion_matrix/standalone/widgets/SymphonyBinaryConfusionMatrix.js.map
symphony_binary_confusion_matrix-1.0.2.data/data/etc/jupyter/nbconfig/notebook.d/symphony_binary_confusion_matrix.json
symphony_binary_confusion_matrix-1.0.2.data/data/share/jupyter/labextensions/symphony-binary-confusion-matrix/build_log.json
symphony_binary_confusion_matrix-1.0.2.data/data/share/jupyter/labextensions/symphony-binary-confusion-matrix/install.json
symphony_binary_confusion_matrix-1.0.2.data/data/share/jupyter/labextensions/symphony-binary-confusion-matrix/package.json
symphony_binary_confusion_matrix-1.0.2.dist-info/LICENSE.txt
symphony_binary_confusion_matrix-1.0.2.dist-info/METADATA
symphony_binary_confusion_matrix-1.0.2.dist-info/WHEEL
symphony_binary_confusion_matrix-1.0.2.dist-info/top_level.txt
symphony_binary_confusion_matrix-1.0.2.dist-info/RECORD
